PaTho/__init__.py
PaTho/downloader.py
PaTho-0.1.1.dist-info/LICENSE
PaTho-0.1.1.dist-info/METADATA
PaTho-0.1.1.dist-info/WHEEL
PaTho-0.1.1.dist-info/entry_points.txt
PaTho-0.1.1.dist-info/top_level.txt
PaTho-0.1.1.dist-info/RECORD
