Metadata-Version: 2.1
Name: PaTho
Version: 0.1.1
Summary: A package to download images from URLs.
Author: Mian Bruel
License-File: LICENSE
Requires-Dist: requests
